Workbook

Sheet Cuestionario
B3: Talento Humano | D3: Respuestas
B4: 1 | C4: Total de empleados de la empresa | D4: 450
B5: 2 | C5: Cantidad de empleados en el exterior | D5: 0
B6: 3 | C6: Cantidad de empleados formados en el exterior | D6: 0
B7: 4 | C7: Cantidad de empleados con competencia en segunda lengua | D7: 0
B8: 5 | C8: Cantidad de empleados extranjeros | D8: 0
B9: 6 | C9: Cantidad de empleados que participen o hayan participado en actividades empresariales en el exterior | D9: 1
B10: 7 | C10: Programa de transferencia de conocimiento de representación/ formación fuera del país | D10: No
B11: 8 | C11: Cantidad de empleados con experiencia en operaciones internacionales | D11: 1
B12: 9 | C12: La empresa cuenta con un plan de formación de talento humano / Incentivos en el exterior | D12: No
B14: Direccionamiento Estratégico | D14: Respuestas
B15: 1 | C15: La empresa tiene definida su estructura organizacional | D15: Si
B16: 2 | C16: La empresa ha definido un plan estratégico de operación | D16: Si
B17: 2.1 | C17: El plan estratégico de la empresa tiene alcance internacional. | D17: Si
B18: 3 | C18: La empresa cuenta con un departamento o dirección para los procesos de internacionalización | D18: Si
B20: Tecnología e Innovación | D20: Respuestas
B21: 1 | C21: La empresa ha participado en proyectos de innovación con empresas internacionales | D21: No
B22: 2 | C22: La empresa ha participado en proyectos de innovación con miras a la internacionalización | D22: No
B23: 3 | C23: La empresa realiza Investigación y Desarrollo de productos/servicios para ser internacionalizados | D23: Si
B24: 4 | C24: La empresa ha adquirido tecnología en el exterior | D24: No
B25: 5 | C25: La empresa realiza inversiones en tecnología e innovación | D25: Si
B26: 5.1 | C26: Porcentaje del presupuesto de la empresa que se destina a inversión en tecnología e innovación | D26: 0.6
B27: 6 | C27: La empresa ha recibido transferencia de conocimiento desde el exterior | D27: No
B29: Sostenibilidad | D29: Respuestas
B30: 1 | C30: La empresa mide su huella de carbono | D30: Si
B31: 1.1 | C31: De acuerdo al tamaño de su empresa, la huella de carbono debería estar en este rango de toneladas de C02 al año. Indique sí está entre ese rango, por debajo o por encima del mismo. | D31: Estoy por encima del rango | E31: =+IF($D$4<=10,"1 a 5",IF($D$4<=50,"5 a 20",IF($D$4<=200,"20 a 100",0))) -> 0
B32: 2 | C32: La empresa cuenta con políticas de equidad de género | D32: Si
B33: 2.1 | C33: Cantidad de mujeres empleadas | D33: 5
B34: 2.2 | C34: Cantidad de mujeres empleadas en cargos directivos | D34: 2
B35: 3 | C35: La empresa cuenta con planes de responsabilidad social empresarial | D35: Si
B36: 4 | C36: La empresa participa en iniciativas globales de sostenibilidad (pacto mundial, agenda 2030, ODS) | D36: No
B37: 4.1 | C37: ¿Cuáles con esas iniciativas globales de sostenibilidad en las que participa la empresa? | D37: Documentar
B38: 5 | C38: La empresa realiza reporte de gestión considerando aspectos sociales, ambientales y económicos | D38: No
B39: 6 | C39: El producto / servicio de la empresa tiene enfoque de sostenibilidad | D39: Si
B40: 6.1 | C40: ¿Cómo se observa el enfoque de sostenibilidad en el producto / servicio de la empresa? | D40: Documentar
B41: 7 | C41: Cuenta con algun programa o inciativa de gestión de proveedores | D41: No
B43: Potencial de internacionalización (modos de entrada) | D43: Respuestas
B44: Exportación e Importación (Bienes)
B45: 1 | C45: La empresa cuenta con plan exportador/importador | D45: Si
B46: 1.1 | C46: Ha recibido acompañamiento institucional para elaborar dicho plan | D46: No
B47: 2 | C47: Ha realizado exportación | D47: Si
B48: 2.1 | C48: De qué forma ha exportado | D48: Directa
B49: 2.2 | C49: Está registrado como exportador | D49: Si
B50: 2.3 | C50: La empresa cuenta con capacidad de producción para exportar | D50: Si
B51: 3 | C51: Número de países a los que exporta | D51: 1 a 3
B52: 4 | C52: Ha realizado importación | D52: Si
B53: 4.1 | C53: Está registrado como importador | D53: Si
B54: 4.2 | C54: Finalidad de la importación | D54: Abastecimiento
B55: 5 | C55: Número de países de los que importa | D55: 1 a 3
B56: Exportación (Servicios)
B57: 1 | C57: ¿La empresa exporta servicios? | D57: No
B58: 1.1 | C58: En qué modalidad | D58: Comercio Transfronterizo
B59: 1.2 | C59: Está registrado como exportador de servicios | D59: No
B60: 2 | C60: Número de países a los que exporta servicios | D60: 0
B61: Inversión Extranjera Directa | D61: Respuestas
B62: 1 | C62: La empresa cuenta con plan de internacionacionalización | D62: No
B63: 2 | C63: La empresa cuenta con filiales en el exterior | D63: No
B64: 3 | C64: La empresa realiza Investigación y Desarrollo para la internacionalización | D64: Si
B65: 4 | C65: La empresa realizó inversión extranjera directa | D65: No
B66: 4.1 | C66: Monto de la inversión extranjera directa que la empresa realizó | D66: 0
B67: 4.2 | C67: Forma en la que realizó la IED | D67: Ninguna
B68: 5 | C68: La empresa recibió inversión extranjera directa | D68: No
B69: 5.1 | C69: Monto de la inversión extranjera directa que la empresa recibió | D69: 0
B70: 6 | C70: La empresa ha participado en licitaciones internacionales | D70: No
B71: 6.1 | C71: ¿Ganó alguno de los procesos de licitaciones internacionales en los que partició? | D71: No
B72: 6.2 | C72: Monto del proceso de licitación internacional que ganó | D72: 0
B73: 7 | C73: Número de países en los que invirtió en el exterior | D73: 0
B74: 8 | C74: Número de países de los que recibió inversión | D74: 0
B75: Licencias y Franquicias
B76: 0 | C76: Considera que el modelo de negocio podría convertirse en franquicia? | D76: No
B77: 1 | C77: La empresa tiene modelo de franquicia | D77: No
B78: 2 | C78: La empresa cuenta con franquicias en el exterior | D78: No
B79: 3 | C79: La empresa ha adquirido franquicias internacionales para operar en el mercado local | D79: No
B80: 4 | C80: La empresa cuenta con licencias (fabricación, distrubución, etc) en el exterior | D80: No
B81: 5 | C81: La empresa cuenta con licencias (fabricación, distrubución, etc) de empresa extranjeras | D81: No
B82: Alianzas estratégicas
B83: 1 | C83: La empresa ha generado alianzas estratégicas con empresas internacionales | D83: Si
B84: 1.1 | C84: Cómo se desarrolló | D84: proveedores de asientos para motos en una empresa de republica dominica
B86: Potencial de internacionalización (Producto/Servicio) | D86: Respuestas
B87: 1 | C87: La capacidad de producción actual permite atender una mayor demanda en mercados internacionales sin comprometer la calidad | D87: Si
B88: 2 | C88: Ha realizado análisis de viabilidad de internacionalización de su producto o servicio | D88: Si
B89: 2.1 | C89: ¿Cuáles son las ventajas competitivas clave para el posicionamiento de su producto/servicio en el mercado internacional? | D89: Diferenciación
B90: 2.3 | C90: Tiene identificada la posición arancelaria de su producto | D90: Si
B91: 2.4 | C91: Conoce los requerimientos locales para la salida de su producto | D91: Si
B92: 3 | C92: ¿Su organización posee patentes obtenidas o en proceso ante la oficina de registro? | D92: No
B93: 4 | C93: ¿Los productos de su organización estan basados en licencias de tecnología? | D93: No
B94: 5 | C94: ¿Los productos de su organización son desarrollos propios? | D94: Si
B95: 6 | C95: ¿Los desarrollos propios son suceptibles de protección? | D95: Si
B96: 7 | C96: Considera que su producto / servicio es fácilmente adaptable a mercados internacionales | D96: Si
B97: 8 | C97: Realiza venta de sus productos/servicios por medio de e-commerce? | D97: Si

Sheet Formulación y Resultados
B2: Ponderación | C2: Talento Humano | E2: Resultado | F2: Ponderación | G2: Resultado de Dimensión
B3: 0.125 | C3: 1 | D3: Total de empleados de la empresa | E3: =IF(Cuestionario!D4>0,Cuestionario!D4,"Ingrese datos") -> 450 | F3: =+IF(E3<=10,"Micro",IF(E3<=50,"Pequeña",IF(E3<=200,"Mediana",0))) -> 0 | G3: =+SUM(F3:F11)*B3 -> 6.9444444e-05 | I3: T.H | J3: =+G3 -> 6.9444444e-05
C4: 2 | D4: Cantidad de empleados en el exterior | E4: =IF(Cuestionario!$D$4>0,+Cuestionario!D5/Cuestionario!$D$4,"Ingrese datos") -> 0 | F4: =+E4*0.125 -> 0 | I4: D.E | J4: =+G13 -> 0.075
C5: 3 | D5: Cantidad de empleados formados en el exterior | E5: =IF(Cuestionario!$D$4>0,+Cuestionario!D6/Cuestionario!$D$4,"Ingrese datos") -> 0 | F5: =+E5*0.125 -> 0 | I5: TeI | J5: =+G18 -> 0.04375
C6: 4 | D6: Cantidad de empleados con competencia en segunda lengua | E6: =IF(Cuestionario!$D$4>0,+Cuestionario!D7/Cuestionario!$D$4,"Ingrese datos") -> 0 | F6: =+E6*0.125 -> 0 | I6: S | J6: =+G26 -> 0.061896825
C7: 5 | D7: Cantidad de empleados extranjeros | E7: =IF(Cuestionario!$D$4>0,+Cuestionario!D8/Cuestionario!$D$4,"Ingrese datos") -> 0 | F7: =+E7*0.125 -> 0 | I7: P.I | J7: =+H38 -> 0.21954167
C8: 6 | D8: Cantidad de empleados que participen o hayan participado en actividades empresariales en el exterior | E8: =IF(Cuestionario!$D$4>0,+Cuestionario!D9/Cuestionario!$D$4,"Ingrese datos") -> 0.0022222222 | F8: =+E8*0.125 -> 0.00027777778 | I8: Expo (Bienes) | J8: =+G39 -> 0.056
C9: 7 | D9: Programa de transferencia de conocimiento de representación/ formación fuera del país | E9: =+IF(Cuestionario!$D$10="Si",100%,0) -> 0 | F9: =+E9*0.125 -> 0 | I9: Expo (servicios) | J9: =+G50 -> 0.0016666667
C10: 8 | D10: Cantidad de empleados con experiencia en operaciones internacionales | E10: =IF(Cuestionario!$D$4>0,+Cuestionario!D11/Cuestionario!$D$4,"Ingrese datos") -> 0.0022222222 | F10: =+E10*0.125 -> 0.00027777778 | I10: IED | J10: =+G56 -> 0.01
C11: 9 | D11: La empresa cuenta con un plan de formación de talento humano / Incentivos en el exterior | E11: =+IF(Cuestionario!$D$12="Si",100%,0) -> 0 | F11: =+E11*0.125 -> 0 | I11: LyF | J11: =+G70 -> 0
B12: Ponderación | C12: Direccionamiento estratégico | E12: Resultado | F12: Ponderación | G12: Resultado de Dimensión | I12: AE | J12: =+G77 -> 0.03
B13: 0.075 | C13: 1 | D13: La empresa tiene definida su estructura organizacional | E13: =+IF(Cuestionario!$D$15="Si",100%,0) -> 1 | F13: =+E13*(1/3) -> 0.33333333 | G13: =+SUM(F13:F16)*B13 -> 0.075 | I13: Prd. | J13: =+G79 -> 0.121875
C14: 2 | D14: La empresa ha definido un plan estratégico de operación | E14: =+IF(Cuestionario!$D$16="Si",100%,0) -> 1 | F14: =+E14*((1/3)/2) -> 0.16666667
C15: 2.1 | D15: El plan estratégico de la empresa tiene alcance internacional. | E15: =+IF(Cuestionario!$D$17="Si",100%,0) -> 1 | F15: =+E15*((1/3)/2) -> 0.16666667
C16: 3 | D16: La empresa cuenta con un departamento o dirección para los procesos de internacionalización | E16: =+IF(Cuestionario!$D$18="Si",100%,0) -> 1 | F16: =+E16*(1/3) -> 0.33333333
B17: Ponderación | C17: Tecnología e innovación | E17: Resultado | F17: Ponderación | G17: Resultado de Dimensión
B18: 0.15 | C18: 1 | D18: La empresa ha participado en proyectos de innovación con empresas internacionales | E18: =+IF(Cuestionario!$D$21="Si",100%,0) -> 0 | F18: =+E18*(1/6) -> 0 | G18: =+SUM(F18:F24)*B18 -> 0.04375
C19: 2 | D19: La empresa ha participado en proyectos de innovación con miras a la internacionalización | E19: =+IF(Cuestionario!$D$22="Si",100%,0) -> 0 | F19: =+E19*(1/6) -> 0
C20: 3 | D20: La empresa realiza Investigación y Desarrollo de productos/servicios para ser internacionalizados | E20: =+IF(Cuestionario!$D$23="Si",100%,0) -> 1 | F20: =+E20*(1/6) -> 0.16666667
C21: 4 | D21: La empresa ha adquirido tecnología en el exterior | E21: =+IF(Cuestionario!$D$24="Si",100%,0) -> 0 | F21: =+E21*(1/6) -> 0
C22: 5 | D22: La empresa realiza inversiones en tecnología e innovación | E22: =+IF(Cuestionario!$D$25="Si",100%,0) -> 1 | F22: =+E22*((1/6)/2) -> 0.083333333
C23: 5.1 | D23: Porcentaje del presupuesto de la empresa que se destina a inversión en tecnología e innovación | E23: =+IF(Cuestionario!$D$26>1%,50%,IF(Cuestionario!$D$26>2%,75%,IF(Cuestionario!$D$26>3%,100%,0))) -> 0.5 | F23: =+E23*((1/6)/2) -> 0.041666667
C24: 6 | D24: La empresa ha recibido transferencia de conocimiento desde el exterior | E24: =+IF(Cuestionario!$E$27="Si",100%,0) -> 0 | F24: =+E24*(1/6) -> 0
B25: Ponderación | C25: Sostenibilidad | E25: Resultado | F25: Ponderación | G25: Resultado de Dimensión
B26: 0.15 | C26: 1 | D26: La empresa mide su huella de carbono | E26: =+IF(Cuestionario!$D$30="Si",100%,0) -> 1 | F26: =+E26*((1/7)/2) -> 0.071428571 | G26: =+SUM(F26:F35)*B26 -> 0.061896825
C27: 1.1 | D27: De acuerdo al tamaño de su empresa, la huella de carbono debería estar en este rango de toneladas de C02 al año. Indique sí está entre ese rango, por debajo o por encima del mismo. | E27: =+IF(Cuestionario!$D$31="Estoy en el rango",90%,IF(Cuestionario!$D$31="Estoy por debajo del rango",100%,IF(Cuestionario!$D$31="Estoy por encima del rango",10%,IF(Cuestionario!$D$31="No realizo medición de CO2",0%,0)))) -> 0.1 | F27: =+E27*((1/7)/2) -> 0.0071428571
C28: 2 | D28: La empresa cuenta con políticas de equidad de género | E28: =+IF(Cuestionario!$D$32="Si",100%,0) -> 1 | F28: =+E28*((1/7)/3) -> 0.047619048
C29: 2.1 | D29: Cantidad de mujeres empleadas | E29: =IF(Cuestionario!$D$4>0,+Cuestionario!D33/Cuestionario!$D$4,"Ingrese datos") -> 0.011111111 | F29: =+E29*((1/7)/3) -> 0.00052910053
C30: 2.2 | D30: Cantidad de mujeres empleadas en cargos directivos | E30: =IF(Cuestionario!$D$4>0,+Cuestionario!D34/Cuestionario!$D$4,"Ingrese datos") -> 0.0044444444 | F30: =+E30*((1/7)/3) -> 0.00021164021
C31: 3 | D31: La empresa cuenta con planes de responsabilidad social empresarial | E31: =+IF(Cuestionario!$D$35="Si",100%,0) -> 1 | F31: =+E31*(1/7) -> 0.14285714
C32: 4 | D32: La empresa participa en iniciativas globales de sostenibilidad (pacto mundial, agenda 2030, ODS) | E32: =+IF(Cuestionario!$D$36="Si",100%,0) -> 0 | F32: =+E32*(1/7) -> 0
C33: 5 | D33: La empresa realiza reporte de gestión considerando aspectos sociales, ambientales y económicos | E33: =+IF(Cuestionario!$D$38="Si",100%,0) -> 0 | F33: =+E33*(1/7) -> 0
C34: 6 | D34: El producto / servicio de la empresa tiene enfoque de sostenibilidad | E34: =+IF(Cuestionario!$D$39="Si",100%,0) -> 1 | F34: =+E34*(1/7) -> 0.14285714
C35: 7 | D35: Cuenta con algun programa o inciativa de gestión de proveedores | E35: =+IF(Cuestionario!$D$41="Si",100%,0) -> 0 | F35: =+E35*(1/7) -> 0
B36: Potencial de internacionalización
B37: Ponderación | C37: Potencial de internacionalización (Modos de entrada) | E37: Resultado | F37: Ponderación | G37: Resultado de subimensión | H37: Resultado de Dimensión
B38: 0.08 | C38: Exportación e Importación | H38: =+G39+G56+G70+G77+G79+G50 -> 0.21954167
C39: 1 | D39: La empresa cuenta con plan exportador/importador | E39: =+IF(Cuestionario!$D$45="Si",100%,0) -> 1 | F39: =+E39*((1/5)/2) -> 0.1 | G39: =+SUM(F39:F49)*B38 -> 0.056
C40: 1.1 | D40: Ha recibido acompañamiento institucional para elaborar dicho plan | E40: =+IF(Cuestionario!$D$46="Si",100%,0) -> 0 | F40: =+E40*((1/5)/2) -> 0
C41: 2 | D41: Ha realizado exportación | E41: =+IF(Cuestionario!$D$47="Si",100%,0) -> 1 | F41: =+E41*((1/5)/4) -> 0.05
C42: 2.1 | D42: De qué forma ha exportado | E42: =+IF(Cuestionario!$D$48="Directa",100%,IF(Cuestionario!$D$48="Indirecta",50%,0)) -> 1 | F42: =+E42*((1/5)/4) -> 0.05
C43: 2.2 | D43: Está registrado como exportador | E43: =+IF(Cuestionario!$D$49="Si",100%,0) -> 1 | F43: =+E43*((1/5)/4) -> 0.05
C44: 2.3 | D44: La empresa cuenta con capacidad de producción para exportar | E44: =+IF(Cuestionario!$D$50="Si",100%,0) -> 1 | F44: =+E44*((1/5)/4) -> 0.05
C45: 3 | D45: Número de países a los que exporta | E45: =+IF(Cuestionario!$D$51="1 a 3",50%,IF(Cuestionario!$D$51="4 a 8",75%,IF(Cuestionario!$D$51="9 o más",100%,0))) -> 0.5 | F45: =+E45*((1/5)) -> 0.1
C46: 4 | D46: Ha realizado importación | E46: =+IF(Cuestionario!$D$52="Si",100%,0) -> 1 | F46: =+E46*((1/5)/3) -> 0.066666667
C47: 4.1 | D47: Está registrado como importador | E47: =+IF(Cuestionario!$D$53="Si",100%,0) -> 1 | F47: =+E47*((1/5)/3) -> 0.066666667
C48: 4.2 | D48: Finalidad de la importación | E48: =+IF(Cuestionario!$D$54="Comercialización",100%,IF(Cuestionario!$D$54="Abastecimiento",100%,0)) -> 1 | F48: =+E48*((1/5)/3) -> 0.066666667
C49: 5 | D49: Número de países desde los que importa | E49: =+IF(Cuestionario!$D$55="1 a 3",50%,IF(Cuestionario!$D$55="4 a 8",75%,IF(Cuestionario!$D$55="9 o más",100%,0))) -> 0.5 | F49: =+E49*((1/5)) -> 0.1
B50: 0.04 | C50: Exportación (Servicios) | G50: =+SUM(F51:F54)*B50 -> 0.0016666667
C51: 1 | D51: ¿La empresa exporta servicios? | E51: =+IF(Cuestionario!$D$57="Si",100%,0) -> 0 | F51: =+E51*((1/2)/3) -> 0
C52: 1.1 | D52: En qué modalidad | E52: =+IF(Cuestionario!D58="Comercio Transfronterizo",25%,IF(Cuestionario!D58="Consumo en el exterior",50%,IF(Cuestionario!D58="Movimiento de Personas",75%,IF(Cuestionario!D58="Presencia Comercial",100%,0)))) -> 0.25 | F52: =+E52*((1/2)/3) -> 0.041666667
C53: 1.2 | D53: Está registrado como exportador de servicios | E53: =+IF(Cuestionario!$D$57="Si",100%,0) -> 0 | F53: =+E53*((1/2)/3) -> 0
C54: 2 | D54: Número de países a los que exporta servicios | E54: =+IF(Cuestionario!$D$60="1 a 3",50%,IF(Cuestionario!$D$60="4 a 8",75%,IF(Cuestionario!$D$60="9 o más",100%,0))) -> 0 | F54: =+E54*((1/2)) -> 0
B55: 0.08 | C55: Inversión Extranjera Directa
C56: 1 | D56: La empresa cuenta con plan de internacionacionalización | E56: =+IF(Cuestionario!$D$62="Si",100%,0) -> 0 | F56: =+E56*((1/8)) -> 0 | G56: =+SUM(F56:F68)*B55 -> 0.01
C57: 2 | D57: La empresa cuenta con filiales en el exterior | E57: =+IF(Cuestionario!$D$63="Si",100%,0) -> 0 | F57: =+E57*((1/8)) -> 0
C58: 3 | D58: La empresa realiza Investigación y Desarrollo para la internacionalización | E58: =+IF(Cuestionario!$D$64="Si",100%,0) -> 1 | F58: =+E58*((1/8)) -> 0.125
C59: 4 | D59: La empresa realizó inversión extranjera directa | E59: =+IF(Cuestionario!$D$65="Si",100%,0) -> 0 | F59: =+E59*((1/8)/3) -> 0
C60: 4.1 | D60: Monto de la inversión extranjera directa que la empresa realizó | E60: =+IF(Cuestionario!$D$66="Hasta 100.000 USD",50%,IF(Cuestionario!$D$66="Entre 100.001 y 500.000 USD",75%,IF(Cuestionario!$D$66="Más de 500.000 USD",100%,0))) -> 0 | F60: =+E60*((1/8)/3) -> 0
C61: 4.2 | D61: Forma en la que realizó la IED | E61: =+IF(Cuestionario!$D$67="Fusión",50%,IF(Cuestionario!$D$67="Adquisición",75%,IF(Cuestionario!$D$67="Greenfield",100%,0))) -> 0 | F61: =+E61*((1/8)/3) -> 0
C62: 5 | D62: La empresa recibió inversión extranjera directa | E62: =+IF(Cuestionario!$D$68="Si",100%,0) -> 0 | F62: =+E62*((1/8)/2) -> 0
C63: 5.1 | D63: Monto de la inversión extranjera directa que la empresa recibió | E63: =+IF(Cuestionario!$D$69="Hasta 100.000 USD",50%,IF(Cuestionario!$D$69="Entre 100.001 y 500.000 USD",75%,IF(Cuestionario!$D$69="Más de 500.000 USD",100%,0))) -> 0 | F63: =+E63*((1/8)/2) -> 0
C64: 6 | D64: La empresa ha participado en licitaciones internacionales | E64: =+IF(Cuestionario!$D$70="Si",100%,0) -> 0 | F64: =+E64*((1/8)/3) -> 0
C65: 6.1 | D65: ¿Ganó alguno de los procesos de licitaciones internacionales en los que partició? | E65: =+IF(Cuestionario!$D$71="Si",100%,0) -> 0 | F65: =+E65*((1/8)/3) -> 0
C66: 6.2 | D66: Monto del proceso de licitación internacional que ganó | E66: =+IF(Cuestionario!$D$72="Hasta 100.000 USD",50%,IF(Cuestionario!$D$72="Entre 100.001 y 500.000 USD",75%,IF(Cuestionario!$D$72="Más de 500.000 USD",100%,0))) -> 0 | F66: =+E66*((1/8)/3) -> 0
C67: 7 | D67: Número de países en los que invirtió en el exterior | E67: =+IF(Cuestionario!$D$73="1 a 3",50%,IF(Cuestionario!$D$73="4 a 8",75%,IF(Cuestionario!$D$73="9 o más",100%,0))) -> 0 | F67: =+E67*((1/8)) -> 0
C68: 8 | D68: Número de países de los que recibió inversión | E68: =+IF(Cuestionario!$D$74="1 a 3",50%,IF(Cuestionario!$D$74="4 a 8",75%,IF(Cuestionario!$D$74="9 o más",100%,0))) -> 0 | F68: =+E68*((1/8)) -> 0
B69: 0.07 | C69: Licencias y Franquicias
C70: 1 | D70: Considera que el modelo de negocio podría convertirse en franquicia? | E70: =+IF(Cuestionario!$D$76="Si",100%,0) -> 0 | F70: =+E70*((1/6)) -> 0 | G70: =+SUM(F70:F75)*B69 -> 0
C71: 2 | D71: La empresa tiene modelo de franquicia | E71: =+IF(Cuestionario!$D$77="Si",100%,0) -> 0 | F71: =+E71*((1/6)) -> 0
C72: 3 | D72: La empresa cuenta con franquicias en el exterior | E72: =+IF(Cuestionario!$D$78="Si",100%,0) -> 0 | F72: =+E72*((1/6)) -> 0
C73: 4 | D73: La empresa ha adquirido franquicias internacionales para operar en el mercado local | E73: =+IF(Cuestionario!$D$79="Si",100%,0) -> 0 | F73: =+E73*((1/6)) -> 0
C74: 5 | D74: La empresa cuenta con licencias (fabricación, distrubución, etc) en el exterior | E74: =+IF(Cuestionario!$D$80="Si",100%,0) -> 0 | F74: =+E74*((1/6)) -> 0
C75: 6 | D75: La empresa cuenta con licencias (fabricación, distrubución, etc) de empresa extranjeras | E75: =+IF(Cuestionario!$D$81="Si",100%,0) -> 0 | F75: =+E75*((1/6)) -> 0
B76: 0.03 | C76: Alianzas estratégicas
C77: 1 | D77: La empresa ha generado alianzas estratégicas con empresas internacionales | E77: =+IF(Cuestionario!$D$83="Si",100%,0) -> 1 | F77: =+E77*(1/1) -> 1 | G77: =+SUM(F77)*B76 -> 0.03
B78: Ponderación | C78: Potencial de internacionalización (Producto/Servicio) | E78: Resultado | F78: Ponderación | G78: Resultado de Dimensión
B79: 0.2 | C79: 1 | D79: La capacidad de producción actual permite atender una mayor demanda en mercados internacionales sin comprometer la calidad | E79: =+IF(Cuestionario!$D$87="Si",100%,0) -> 1 | F79: =+E79*((1/8)) -> 0.125 | G79: =+SUM(F79:F88)*B79 -> 0.121875
C80: 2 | D80: Ha realizado análisis de viabilidad de internacionalización de su producto o servicio | E80: =+IF(Cuestionario!$D$88="Si",100%,0) -> 1 | F80: =+E80*((1/8)/4) -> 0.03125
C81: 2.1 | D81: Cuáles son las ventajas competitivas clave para el posicionamiento de su producto/servicio en el mercado internacional | E81: =+IF(Cuestionario!$D$89="Diferenciación",50%,IF(Cuestionario!$D$89="Precio",75%,IF(Cuestionario!$D$89="Competencia",100%,0))) -> 0.5 | F81: =+E81*((1/8)/4) -> 0.015625
C82: 2.3 | D82: Tiene identificada la posición arancelaria de su producto | E82: =+IF(Cuestionario!$D$90="Si",100%,0) -> 1 | F82: =+E82*((1/8)/4) -> 0.03125
C83: 2.4 | D83: Conoce los requerimientos locales para la salida de su producto | E83: =+IF(Cuestionario!$D$91="Si",100%,0) -> 1 | F83: =+E83*((1/8)/4) -> 0.03125
C84: 3 | D84: Su organización posee patentes obtenidas o en proceso ante la oficina de registro? | E84: =+IF(Cuestionario!$D$92="Si",100%,0) -> 0 | F84: =+E84*((1/8)) -> 0
C85: 4 | D85: Los productos de su organización estan basados en licencias de tecnología? | E85: =+IF(Cuestionario!$D$93="Si",100%,0) -> 0 | F85: =+E85*((1/8)) -> 0
C86: 5 | D86: Los productos de su organización son desarrollos propios? | E86: =+IF(Cuestionario!$D$94="Si",100%,0) -> 1 | F86: =+E86*((1/8)) -> 0.125
C87: 6 | D87: Los desarrollos propios son suceptibles de protección? | E87: =+IF(Cuestionario!$D$95="Si",100%,0) -> 1 | F87: =+E87*((1/8)) -> 0.125
C88: 7 | D88: Considera que su producto / servicio es fácilmente adaptable a mercados internacionales | E88: =+IF(Cuestionario!$D$96="Si",100%,0) -> 1 | F88: =+E88*((1/8)) -> 0.125
C89: 8 | D89: Realiza venta de sus productos/servicios por medio de e-commerce? | E89: =+IF(Cuestionario!$D$97="Si",100%,0) -> 1 | F89: =+E89*((1/8)) -> 0.125

Sheet Resultados
B4: Dimensiones | C4: Puntaje Obtenido | D4: Puntaje Máximo | E4: Estandarización 1 | F4: Estandarización 2
B5: Talento Humano | C5: =+'Formulación y Resultados'!J3 -> 6.9444444e-05 | D5: 0.125 | E5: =+C5/D5 -> 0.00055555556 | F5: 1
B6: Direccionamiento estratégico | C6: =+'Formulación y Resultados'!J4 -> 0.075 | D6: 0.075 | E6: =+C6/D6 -> 1 | F6: 1
B7: Tecnología e innovación | C7: =+'Formulación y Resultados'!J5 -> 0.04375 | D7: 0.15 | E7: =+C7/D7 -> 0.29166667 | F7: 1
B8: Sostenibilidad | C8: =+'Formulación y Resultados'!J6 -> 0.061896825 | D8: 0.15 | E8: =+C8/D8 -> 0.4126455 | F8: 1
B9: Potencial de internacionalización | C9: =+'Formulación y Resultados'!J7 -> 0.21954167 | D9: 0.5 | E9: =+C9/D9 -> 0.43908333 | F9: 1
B10: Modos de entrada | C10: =+SUM(C11:C15) -> 0.097666667 | D10: 0.3 | E10: =+C10/D10 -> 0.32555556 | F10: 1
B11: Exportación e Importación (Bienes) | C11: =+'Formulación y Resultados'!J8 -> 0.056 | D11: 0.08 | E11: =+C11/D11 -> 0.7 | F11: 1
B12: Exportación (Servicios) | C12: =+'Formulación y Resultados'!J9 -> 0.0016666667 | D12: 0.04 | E12: =+C12/D12 -> 0.041666667 | F12: 1
B13: Inversión Extranjera Directa | C13: =+'Formulación y Resultados'!J10 -> 0.01 | D13: 0.08 | E13: =+C13/D13 -> 0.125 | F13: 1
B14: Licencias y Franquicias | C14: =+'Formulación y Resultados'!J11 -> 0 | D14: 0.07 | E14: =+C14/D14 -> 0 | F14: 1
B15: Alianzas Estratégicas | C15: =+'Formulación y Resultados'!J12 -> 0.03 | D15: 0.03 | E15: =+C15/D15 -> 1 | F15: 1
B16: Producto/Servicio | C16: =+'Formulación y Resultados'!J13 -> 0.121875 | D16: 0.2 | E16: =+C16/D16 -> 0.609375 | F16: 1
B17: Puntaje total del diagnóstico | C17: =+C5+C6+C7+C8+C9 -> 0.40025794 | D17: =+D5+D6+D7+D8+D9 -> 1

Sheet Ponderación
B1: =SUM(B2:B10) -> 1
B2: 0.125 | C2: Talento Humano
B3: 0.075 | C3: Direccionamiento estratégico
B4: 0.3 | C4: Potencial de internacionalización (modos de entrada)
B5: 0.2 | C5: Potencial de internacionalización (Producto/Servicio)
B6: 0.15 | C6: Tecnología e innovación
B7: 0.15 | C7: Sostenibilidad
B10: Expertos
B11: Profes
B12: Aliados
B13: Profes Externos

Sheet Datos
B1: Rango CO2
B2: No realizo medición de CO2
B3: Estoy en el rango
B4: Estoy por debajo del rango
B5: Estoy por encima del rango
B7: Si
B8: No
B10: Directa
B11: Indirecta
B14: No importa
B15: Comercialización
B16: Abastecimiento
... B26: Competencia
B29: 0
B30: 1 a 3
B31: 4 a 8
B32: 9 o más
B34: 0
B35: Hasta 100.000 USD
B36: Entre 100.001 y 500.000 USD
B37: Más de 500.000 USD
B39: Comercio Transfronterizo
B40: Consumo en el Exterior
B41: Presencia Comercial
B42: Movimiento de Personas
